dash_enterprise_auth/__init__.py
dash_enterprise_auth/version.py
dash_enterprise_auth-0.2.5.dist-info/LICENSE
dash_enterprise_auth-0.2.5.dist-info/METADATA
dash_enterprise_auth-0.2.5.dist-info/WHEEL
dash_enterprise_auth-0.2.5.dist-info/top_level.txt
dash_enterprise_auth-0.2.5.dist-info/RECORD
