Metadata-Version: 2.1
Name: dash-enterprise-auth
Version: 0.2.5
Summary: Authentication integrations for apps using Dash Enterprise
Home-page: https://plotly.com/dash
Author: Antoine Roy-Gobeil
Author-email: antoine@plotly.com
License: MIT
Keywords: dash dash-enterprise dash-auth plotly
Platform: UNKNOWN
Classifier: License :: OSI Approved :: MIT License
Classifier: Framework :: Dash
Classifier: Programming Language :: Python
Classifier: Programming Language :: Python :: 3
Classifier: Programming Language :: Python :: 3.6
Classifier: Programming Language :: Python :: 3.7
Classifier: Programming Language :: Python :: 3.8
Classifier: Programming Language :: Python :: 3.9
Classifier: Programming Language :: Python :: 3.10
Classifier: Programming Language :: Python :: 3.11
Requires-Python: >=3.6
License-File: LICENSE
Requires-Dist: dash
Requires-Dist: Flask <3.1,>=1.0.4
Requires-Dist: Werkzeug <3.1
Requires-Dist: requests[security]
Requires-Dist: PyJWT
Requires-Dist: cryptography <3.4 ; python_version < "3.7"
Requires-Dist: cryptography ; python_version >= "3.7"
